{
    "name": "Custom House/Harper Collins",
    "url": "http://goodreads-exporter.glitch.me/library.json",
    "books": [
        {
            "title": "The Spider Network: The Wild Story of a Math Genius, a Gang of Backstabbing Bankers, and One of the Greatest Scams in Financial History",
            "id": "30759083",
            "author": "David Enrich",
            "date_finished": null,
            "notes": [],
            "date_started": 1514491706000,
            "last_updated": null,
            "reviews": [],
            "links": [
                {
                    "url": "https://www.goodreads.com/book/show/30759083",
                    "last_accessed": null,
                    "type": "external"
                }
            ],
            "publisher": "Custom House/Harper Collins",
            "tags": [
                "Hardcover",
                "Custom House/Harper Collins",
                "to-read"
            ],
            "bookIds": [
                {
                    "type": "ISBN",
                    "id": "0753557495",
                    "note": null
                },
                {
                    "type": "ISBN13",
                    "id": "9780753557495",
                    "note": null
                },
                {
                    "type": "GOODREADS",
                    "id": "30759083",
                    "note": null
                },
                {
                    "type": "BCID",
                    "id": null,
                    "note": null
                }
            ]
        }
    ]
}