{
    "title": "Post-Artifact Books and Publishing",
    "id": "12547419",
    "author": "Craig Mod",
    "date_finished": null,
    "notes": [],
    "date_started": null,
    "last_updated": null,
    "reviews": [],
    "links": [
        {
            "url": "https://www.goodreads.com/book/show/12547419",
            "last_accessed": null,
            "type": "external"
        }
    ],
    "publisher": {},
    "tags": [
        "Kindle Edition",
        "to-read"
    ],
    "bookIds": [
        {
            "type": "ISBN",
            "id": "",
            "note": null
        },
        {
            "type": "ISBN13",
            "id": "",
            "note": null
        },
        {
            "type": "GOODREADS",
            "id": "12547419",
            "note": null
        },
        {
            "type": "BCID",
            "id": null,
            "note": null
        }
    ]
}