{
    "title": "Bailout: An Inside Account of How Washington Abandoned Main Street While Rescuing Wall Street",
    "id": 15737379,
    "author": "Neil Barofsky",
    "date_finished": null,
    "notes": [],
    "date_started": null,
    "last_updated": null,
    "reviews": [],
    "links": [
        {
            "url": "https://www.goodreads.com/book/show/15737379",
            "last_accessed": null,
            "type": "external"
        }
    ],
    "publisher": "Free Press/Simon & Schuster, Inc. (NYC)",
    "tags": [
        "Hardcover",
        "Free Press/Simon & Schuster, Inc. (NYC)",
        "to-read"
    ],
    "bookIds": [
        {
            "type": "ISBN",
            "id": false,
            "note": null
        },
        {
            "type": "ISBN13",
            "id": false,
            "note": null
        },
        {
            "type": "GOODREADS",
            "id": 15737379,
            "note": null
        },
        {
            "type": "BCID",
            "id": null,
            "note": null
        }
    ]
}