{
    "title": "Voyage in Noise: Warren Ellis and the Demise of Western Civilization",
    "id": "18395759",
    "author": "Kevin Thurman, Julian Darius, Warren Ellis",
    "date_finished": null,
    "notes": [],
    "date_started": null,
    "last_updated": null,
    "reviews": [],
    "links": [
        {
            "url": "https://www.goodreads.com/book/show/18395759",
            "last_accessed": null,
            "type": "external"
        }
    ],
    "publisher": "Sequart Research & Literacy Organization",
    "tags": [
        "Kindle Edition",
        "Sequart Research & Literacy Organization",
        "to-read"
    ],
    "bookIds": [
        {
            "type": "ISBN",
            "id": "",
            "note": null
        },
        {
            "type": "ISBN13",
            "id": "",
            "note": null
        },
        {
            "type": "GOODREADS",
            "id": "18395759",
            "note": null
        },
        {
            "type": "BCID",
            "id": null,
            "note": null
        }
    ]
}