{
    "title": "Night Watch (Discworld, #29; City Watch, #6)",
    "id": 47989,
    "author": "Terry Pratchett",
    "date_finished": null,
    "notes": [],
    "date_started": null,
    "last_updated": null,
    "reviews": [],
    "links": [
        {
            "url": "https://www.goodreads.com/book/show/47989",
            "last_accessed": null,
            "type": "external"
        }
    ],
    "publisher": {},
    "tags": [
        "to-read"
    ],
    "bookIds": [
        {
            "type": "ISBN",
            "id": "055215430X",
            "note": null
        },
        {
            "type": "ISBN13",
            "id": false,
            "note": null
        },
        {
            "type": "GOODREADS",
            "id": 47989,
            "note": null
        },
        {
            "type": "BCID",
            "id": null,
            "note": null
        }
    ]
}