{
    "title": "Infinite Jest",
    "id": 6759,
    "author": "David Foster Wallace",
    "date_finished": null,
    "notes": [],
    "date_started": null,
    "last_updated": null,
    "reviews": [],
    "links": [
        {
            "url": "https://www.goodreads.com/book/show/6759",
            "last_accessed": null,
            "type": "external"
        }
    ],
    "publisher": "Back Bay Books",
    "tags": [
        "Paperback",
        "Back Bay Books",
        "to-read"
    ],
    "bookIds": [
        {
            "type": "ISBN",
            "id": false,
            "note": null
        },
        {
            "type": "ISBN13",
            "id": false,
            "note": null
        },
        {
            "type": "GOODREADS",
            "id": 6759,
            "note": null
        },
        {
            "type": "BCID",
            "id": null,
            "note": null
        }
    ]
}