{
    "title": "Phonogram, Vol. 1: Rue Britannia (Phonogram, #1)",
    "id": 848837,
    "author": "Kieron Gillen",
    "date_finished": null,
    "notes": [],
    "date_started": null,
    "last_updated": null,
    "reviews": [],
    "links": [
        {
            "url": "https://www.goodreads.com/book/show/848837",
            "last_accessed": null,
            "type": "external"
        }
    ],
    "publisher": "Image Comics",
    "tags": [
        "Paperback",
        "Image Comics",
        "to-read"
    ],
    "bookIds": [
        {
            "type": "ISBN",
            "id": false,
            "note": null
        },
        {
            "type": "ISBN13",
            "id": false,
            "note": null
        },
        {
            "type": "GOODREADS",
            "id": 848837,
            "note": null
        },
        {
            "type": "BCID",
            "id": null,
            "note": null
        }
    ]
}